moodspeak_ai/__init__.py
moodspeak_ai/core.py
moodspeak_ai-1.0.0.dist-info/METADATA
moodspeak_ai-1.0.0.dist-info/WHEEL
moodspeak_ai-1.0.0.dist-info/top_level.txt
moodspeak_ai-1.0.0.dist-info/RECORD
