Metadata-Version: 2.4
Name: moodspeak-ai
Version: 1.0.0
Summary: A creative emotion-aware AI helper library
Requires-Python: >=3.8
Requires-Dist: openai>=1.0.0
